cdk8s_argocd_resources/__init__.py
cdk8s_argocd_resources/py.typed
cdk8s_argocd_resources/_jsii/__init__.py
cdk8s_argocd_resources/_jsii/cdk8s-argocd-resources@0.0.5.jsii.tgz
cdk8s_argocd_resources/k8s/__init__.py
cdk8s_argocd_resources-0.0.5.dist-info/LICENSE
cdk8s_argocd_resources-0.0.5.dist-info/METADATA
cdk8s_argocd_resources-0.0.5.dist-info/WHEEL
cdk8s_argocd_resources-0.0.5.dist-info/top_level.txt
cdk8s_argocd_resources-0.0.5.dist-info/RECORD
