Metadata-Version: 2.1
Name: cdk8s-argocd-resources
Version: 0.0.5
Summary: @opencdk8s/cdk8s-argocd-resources
Home-page: https://github.com/opencdk8s/cdk8s-argocd-resources
Author: Hunter-Thompson<aatman@auroville.org.in>
License: Apache-2.0
Project-URL: Source, https://github.com/opencdk8s/cdk8s-argocd-resources
Classifier: Intended Audience :: Developers
Classifier: Operating System :: OS Independent
Classifier: Programming Language :: JavaScript
Classifier: Programming Language :: Python :: 3 :: Only
Classifier: Programming Language :: Python :: 3.6
Classifier: Programming Language :: Python :: 3.7
Classifier: Programming Language :: Python :: 3.8
Classifier: Programming Language :: Python :: 3.9
Classifier: Typing :: Typed
Classifier: Development Status :: 4 - Beta
Classifier: License :: OSI Approved
Requires-Python: >=3.6
License-File: LICENSE
Requires-Dist: cdk8s (<3.0.0,>=2.2.74)
Requires-Dist: constructs (<11.0.0,>=10.0.5)
Requires-Dist: jsii (<2.0.0,>=1.50.0)
Requires-Dist: publication (>=0.0.3)
